CHANGES.rst
LICENSE
MANIFEST.in
README.rst
TODO.rst
requirements.txt
setup.cfg
setup.py
test-requirements.txt
blockade/__init__.py
blockade/audit.py
blockade/chaos.py
blockade/cli.py
blockade/config.py
blockade/core.py
blockade/errors.py
blockade/host.py
blockade/net.py
blockade/state.py
blockade/state_machine.py
blockade/utils.py
blockade/version.py
blockade.egg-info/PKG-INFO
blockade.egg-info/SOURCES.txt
blockade.egg-info/dependency_links.txt
blockade.egg-info/entry_points.txt
blockade.egg-info/not-zip-safe
blockade.egg-info/requires.txt
blockade.egg-info/top_level.txt
blockade/api/__init__.py
blockade/api/manager.py
blockade/api/rest.py
blockade/tests/__init__.py
blockade/tests/helpers.py
blockade/tests/test_audit.py
blockade/tests/test_chaos.py
blockade/tests/test_cli.py
blockade/tests/test_config.py
blockade/tests/test_core.py
blockade/tests/test_host.py
blockade/tests/test_integration.py
blockade/tests/test_integration_rest.py
blockade/tests/test_net.py
blockade/tests/test_rest.py
blockade/tests/test_state.py
blockade/tests/util.py