Metadata-Version: 1.1
Name: blockade
Version: 0.4.0
Summary: Blockade: network fault testing with Docker
Home-page: https://github.com/worstcase/blockade
Author: David LaBissoniere
Author-email: david@labisso.com
License: UNKNOWN
Platform: UNKNOWN
Classifier: Development Status :: 3 - Alpha
Classifier: Intended Audience :: Developers
Classifier: Natural Language :: English
Classifier: License :: OSI Approved :: Apache Software License
Classifier: Programming Language :: Python
Classifier: Programming Language :: Python :: 2.6
Classifier: Programming Language :: Python :: 2.7
Classifier: Programming Language :: Python :: 3.2
Classifier: Programming Language :: Python :: 3.3
